dir_tree/__init__.py
dir_tree/_nbdev.py
dir_tree/dir_tree.py
dir_tree-0.0.2.dist-info/LICENSE
dir_tree-0.0.2.dist-info/METADATA
dir_tree-0.0.2.dist-info/WHEEL
dir_tree-0.0.2.dist-info/entry_points.txt
dir_tree-0.0.2.dist-info/top_level.txt
dir_tree-0.0.2.dist-info/RECORD
