Metadata-Version: 2.1
Name: dir-tree
Version: 0.0.2
Summary: Print directory tree.
Home-page: https://github.com/ayasyrev/dir_tree
Author: Andrei Yasyrev
Author-email: a.yasyrev@gmail.com
License: Apache Software License 2.0
Keywords: file system,directory tree.
Platform: UNKNOWN
Classifier: Development Status :: 3 - Alpha
Classifier: Intended Audience :: Developers
Classifier: License :: OSI Approved :: Apache Software License
Classifier: Natural Language :: English
Classifier: Programming Language :: Python :: 3.6
Classifier: Programming Language :: Python :: 3.7
Classifier: Programming Language :: Python :: 3.8
Requires-Python: >=3.6
